pycogat/__init__.py
pycogat/cogat.py
pycogat-0.2.2.dist-info/licenses/LICENSE
pycogat-0.2.2.dist-info/METADATA
pycogat-0.2.2.dist-info/WHEEL
pycogat-0.2.2.dist-info/top_level.txt
pycogat-0.2.2.dist-info/RECORD
