Metadata-Version: 2.4
Name: pycogat
Version: 0.2.2
Summary: Splits CogAT score report PDF export into single page PDFs and labels output by the ID extracted from the PDF.
Author-email: Tyrone O'Garro Jr <t.ogarro94@gmail.com>
License-Expression: MIT
Classifier: Programming Language :: Python :: 3
Classifier: Programming Language :: Python :: 3.10
Classifier: Programming Language :: Python :: 3.11
Classifier: Programming Language :: Python :: 3.12
Classifier: Operating System :: OS Independent
Requires-Python: >=3.10
License-File: LICENSE
Requires-Dist: pandas>=2.0
Requires-Dist: pdfplumber>=0.11.9
Requires-Dist: pypdf>=3.9.1
Requires-Dist: numpy>=1.24
Provides-Extra: test
Requires-Dist: pytest>=7.0.0; extra == "test"
Requires-Dist: pytest-cov; extra == "test"
Requires-Dist: pandas>=2.0; extra == "test"
Requires-Dist: pdfplumber>=0.11.9; extra == "test"
Requires-Dist: pypdf>=3.9.1; extra == "test"
Requires-Dist: numpy>=1.24; extra == "test"
Dynamic: license-file
